AardvarkLibrary/__init__.py
AardvarkLibrary/library.py
AardvarkLibrary/utils.py
AardvarkLibrary/version.py
robotframework_aardvarklibrary-0.2.1.dist-info/AUTHORS
robotframework_aardvarklibrary-0.2.1.dist-info/COPYING
robotframework_aardvarklibrary-0.2.1.dist-info/METADATA
robotframework_aardvarklibrary-0.2.1.dist-info/WHEEL
robotframework_aardvarklibrary-0.2.1.dist-info/top_level.txt
robotframework_aardvarklibrary-0.2.1.dist-info/RECORD
