Metadata-Version: 2.1
Name: robotframework-aardvarklibrary
Version: 0.2.1
Summary: Aardvark Library for Robot Framework
Author-email: michael.walle@kontron.com
License: Apache License 2.0
Classifier: Development Status :: 4 - Beta
Classifier: Framework :: Robot Framework
Classifier: License :: OSI Approved :: Apache Software License
Classifier: Operating System :: OS Independent
Classifier: Programming Language :: Python
Classifier: Topic :: Software Development :: Testing
License-File: COPYING
License-File: AUTHORS
Requires-Dist: robotframework
Requires-Dist: pyaardvark (>=0.2.1)
